lang_wrapper_for_rag/__init__.py
lang_wrapper_for_rag/docs/fe/README.md
lang_wrapper_for_rag/docs/fe/layout.tsx
lang_wrapper_for_rag/docs/fe/package.json
lang_wrapper_for_rag/docs/fe/page.tsx
lang_wrapper_for_rag/docs/hr_policies.pdf
lang_wrapper_for_rag/lang_wrapper_for_rag.py
lang_wrapper_for_rag-0.0.1.dist-info/METADATA
lang_wrapper_for_rag-0.0.1.dist-info/WHEEL
lang_wrapper_for_rag-0.0.1.dist-info/RECORD
