Metadata-Version: 2.4
Name: lang-wrapper-for-rag
Version: 0.0.1
Summary: A modern and secure RAG chatbot using FastAPI and LangChain.
Author: Your Name
Author-email: you@example.com
Requires-Python: >=3.10,<4.0
Classifier: Programming Language :: Python :: 3
Classifier: Programming Language :: Python :: 3.10
Classifier: Programming Language :: Python :: 3.11
Classifier: Programming Language :: Python :: 3.12
Classifier: Programming Language :: Python :: 3.13
Classifier: Programming Language :: Python :: 3.14
Requires-Dist: chromadb (>=0.5.0,<0.6.0)
Requires-Dist: faker (>=38.0.0,<39.0.0)
Requires-Dist: fastapi (>=0.111.0,<0.112.0)
Requires-Dist: langchain (>=0.2.0,<0.3.0)
Requires-Dist: langchain-experimental (>=0.0.60,<0.0.61)
Requires-Dist: langchain-openai (>=0.1.7,<0.2.0)
Requires-Dist: presidio-analyzer (>=2.2.35,<3.0.0)
Requires-Dist: presidio-anonymizer (>=2.2.35,<3.0.0)
Requires-Dist: pydantic (>=2.7.0,<3.0.0)
Requires-Dist: pypdf (>=4.2.0,<5.0.0)
Requires-Dist: slowapi (>=0.1.9,<0.2.0)
Requires-Dist: spacy (>=3.0.0,<4.0.0)
Requires-Dist: tiktoken (>=0.7.0,<0.8.0)
Requires-Dist: uvicorn[standard] (>=0.30.0,<0.31.0)
